{
    "clusterName": "LocalSetUp_ThreeNodeOneDisk_OnePartitionThreeReplicas",
    "version": 1,
    "partitions": [
        {
            "id": 0,
            "partitionClass": "max-replicas-all-datacenters",
            "partitionState": "READ_WRITE",
            "replicaCapacityInBytes": 10737418240,
            "replicas": [
                {
                    "hostname": "localhost",
                    "mountPath": "/tmp/1",
                    "port": 6670
                },
                {
                    "hostname": "localhost",
                    "mountPath": "/tmp/2",
                    "port": 6671
                },
                {
                    "hostname": "localhost",
                    "mountPath": "/tmp/3",
                    "port": 6672
                }
            ]
        }
    ]
}
